{"operacion":"generar_comprobante","tipo_de_comprobante":1,"serie":"FFF3","numero":1,"sunat_transaction":1,"cliente_tipo_de_documento":"6","cliente_numero_de_documento":"20101950710","cliente_denominacion":"TERESOPOLIS S A","cliente_direccion":"AV. AV DEL EJERCITO NRO. 1146 INT. 1508 - LIMA LIMA  MAGDALENA DEL MAR","cliente_email":"alexis.vidal@vilocru.com","cliente_email_1":"","cliente_email_2":"","fecha_de_emision":"\/Date(1621314000000)\/","fecha_de_vencimiento":"\/Date(1622437200000)\/","moneda":2,"tipo_de_cambio":"","porcentaje_de_igv":18,"descuento_global":"","total_descuento":"","total_anticipo":"","total_gravada":13135.59,"total_inafecta":0,"total_exonerada":0,"total_igv":2364.41,"total_gratuita":0,"total_otros_cargos":"","total":15500,"percepcion_tipo":"","percepcion_base_imponible":"","total_percepcion":"","total_incluido_percepcion":null,"detraccion":false,"observaciones":"","documento_que_se_modifica_tipo":"","documento_que_se_modifica_serie":"","documento_que_se_modifica_numero":"","tipo_de_nota_de_credito":"","tipo_de_nota_de_debito":"","enviar_automaticamente_a_la_sunat":true,"enviar_automaticamente_al_cliente":true,"codigo_unico":"","condiciones_de_pago":"","medio_de_pago":"","placa_vehiculo":"","orden_compra_servicio":"","tabla_personalizada_codigo":"","formato_de_pdf":"","motivo":null,"items":[{"unidad_de_medida":"ZZ","codigo":"P0000001","descripcion":"SERVICIO DE REEMPLAZO DE MANGAS POR BRAZOS DE CARGA EM ZONA DE DESPACHO DE GLP DE PLANTA DE VENTAS TALARA","cantidad":1,"valor_unitario":13135.59,"precio_unitario":15500,"descuento":"","subtotal":13135.59,"tipo_de_igv":1,"igv":2364.41,"total":15500,"anticipo_regularizacion":false,"anticipo_comprobante_serie":"","anticipo_comprobante_numero":"","codigo_producto_sunat":"        "}],"guias":null}