{"operacion":"generar_comprobante","tipo_de_comprobante":3,"serie":"FFF2","numero":3,"sunat_transaction":1,"cliente_tipo_de_documento":"6","cliente_numero_de_documento":"20276095201","cliente_denominacion":"DEMETRIO MUNIVE MUEDAS EIRL","cliente_direccion":"MZA. A LOTE. 01 A.H. LUCIANO CASTILLO (AL COSTADO DE DISTRIBUIDORA BACKUS) PIURA - TALARA - PARIÑAS","cliente_email":"alexis.vidal@vilocru.com","cliente_email_1":"","cliente_email_2":"","fecha_de_emision":"\/Date(1620882000000)\/","fecha_de_vencimiento":"\/Date(1620882000000)\/","moneda":1,"tipo_de_cambio":"","porcentaje_de_igv":18,"descuento_global":"","total_descuento":"","total_anticipo":"","total_gravada":7205.08,"total_inafecta":0,"total_exonerada":0,"total_igv":1296.92,"total_gratuita":100,"total_otros_cargos":"","total":8502,"percepcion_tipo":"","percepcion_base_imponible":"","total_percepcion":"","total_incluido_percepcion":null,"detraccion":false,"observaciones":"","documento_que_se_modifica_tipo":1,"documento_que_se_modifica_serie":"FFF3","documento_que_se_modifica_numero":"0000004","tipo_de_nota_de_credito":1,"tipo_de_nota_de_debito":"","enviar_automaticamente_a_la_sunat":true,"enviar_automaticamente_al_cliente":false,"codigo_unico":"","condiciones_de_pago":"","medio_de_pago":"","placa_vehiculo":"","orden_compra_servicio":"","tabla_personalizada_codigo":"","formato_de_pdf":"","motivo":null,"items":[{"unidad_de_medida":"ZZ","codigo":"P0000001","descripcion":"SERVICIO DE REEMPLAZO DE MANGAS POR BRAZOS DE CARGA EM ZONA DE DESPACHO DE GLP DE PLANTA DE VENTAS TALARA","cantidad":1,"valor_unitario":7205.08,"precio_unitario":8502,"descuento":"","subtotal":7205.08,"tipo_de_igv":1,"igv":1296.92,"total":8502,"anticipo_regularizacion":false,"anticipo_comprobante_serie":"","anticipo_comprobante_numero":"","codigo_producto_sunat":"        "},{"unidad_de_medida":"ZZ","codigo":"P0000002","descripcion":"SERVICIO BIENAL DE MANTENIMIENTO DE EQUIPOS MECANICO Y ELECTRICOS DE PLANTA PIURA, PLANTA TALARA Y PLANTA AEROPUERTO EN REFINERIA TALARA","cantidad":1,"valor_unitario":100,"precio_unitario":100,"descuento":"","subtotal":100,"tipo_de_igv":2,"igv":0,"total":100,"anticipo_regularizacion":false,"anticipo_comprobante_serie":"","anticipo_comprobante_numero":"","codigo_producto_sunat":"        "}],"guias":null}